supersat/__init__.py
supersat/loss.py
supersat/model.py
supersat/utils.py
supersat-0.0.5.dist-info/LICENSE
supersat-0.0.5.dist-info/WHEEL
supersat-0.0.5.dist-info/METADATA
supersat-0.0.5.dist-info/RECORD
