Metadata-Version: 2.1
Name: supersat
Version: 0.0.5
Summary: A python package to super-resolve your remote sensing imagery
Home-page: https://github.com/csaybar/supersat
Author: Cesar Aybar
Author-email: fcesar.aybar@uv.es
Requires-Python: >=3.9,<4.0
Classifier: Programming Language :: Python :: 3
Classifier: Programming Language :: Python :: 3.9
Classifier: Programming Language :: Python :: 3.10
Requires-Dist: torch (>=2.0.0)
Project-URL: Documentation, https://csaybar.github.io/supersat/
Project-URL: Repository, https://github.com/csaybar/supersat
